vvmake/__init__.py
vvmake/test.py
vvmake/vv.py
vvmake/vvmake.py
vvmakelib/__init__.py
vvmakelib/test.py
vvmakelib/vv.py
vvmakelib/vvmake.py
vvmake-0.3.5.dist-info/METADATA
vvmake-0.3.5.dist-info/WHEEL
vvmake-0.3.5.dist-info/entry_points.txt
vvmake-0.3.5.dist-info/top_level.txt
vvmake-0.3.5.dist-info/RECORD
