Metadata-Version: 2.1
Name: vvmake
Version: 0.3.5
Summary: This is automation tools
Home-page: https://github.com/shelltdf/vvmake
Author: will
Author-email: shell_tdf@126.com
License: UNKNOWN
Platform: UNKNOWN
